LICENSE
MANIFEST.in
README.rst
setup.py
bin/rpi-doorman
init.d/rpi-doorman.conf
init.d/rpi-doorman.service
rpi_doorman/__init__.py
rpi_doorman/main.py
rpi_doorman/rpi_doorman.py
rpi_doorman.egg-info/PKG-INFO
rpi_doorman.egg-info/SOURCES.txt
rpi_doorman.egg-info/dependency_links.txt
rpi_doorman.egg-info/requires.txt
rpi_doorman.egg-info/top_level.txt
test/test_all.py
test/test_doorman_object.py