Metadata-Version: 1.1
Name: rpi-doorman
Version: 0.1.1
Summary: Door state monitor
Home-page: https://github.com/ricco386/rpi-doorman/
Author: Richard Kellner
Author-email: richard.kellner [at] gmail.com
License: MIT
Platform: any
Classifier: Environment :: Console
Classifier: Intended Audience :: System Administrators
Classifier: Intended Audience :: Developers
Classifier: Operating System :: Unix
Classifier: Operating System :: POSIX :: Linux
Classifier: License :: OSI Approved :: MIT License
Classifier: Programming Language :: Python
Classifier: Programming Language :: Python :: 2
Classifier: Programming Language :: Python :: 3
Classifier: Development Status :: 3 - Alpha
Classifier: Topic :: Utilities
